logitest/__init__.py
logitest/assertion.py
logitest/cleanup_decorators.py
logitest/config.py
logitest/create_conftest.py
logitest/data_handler.py
logitest/decorators.py
logitest/del_pycache.py
logitest/generate_tests.py
logitest/helper.py
logitest/insert_decorators.py
logitest-0.1.3.dist-info/LICENSE
logitest-0.1.3.dist-info/METADATA
logitest-0.1.3.dist-info/WHEEL
logitest-0.1.3.dist-info/entry_points.txt
logitest-0.1.3.dist-info/top_level.txt
logitest-0.1.3.dist-info/RECORD
