Metadata-Version: 2.1
Name: logitest
Version: 0.1.3
Summary: Automated test case generation tool for Python modules.
Home-page: https://github.com/saisrinivas-samoju/logitest
Author: Sai Srinivas
Author-email: saisrinivas.samoju@example.com
Classifier: Programming Language :: Python :: 3
Classifier: License :: OSI Approved :: MIT License
Classifier: Operating System :: OS Independent
Requires-Python: >=3.9
License-File: LICENSE
Requires-Dist: pytest
Requires-Dist: joblib
Requires-Dist: dill
